requests_http_signature/__init__.py
requests_http_signature_jaywink-0.1.0.dev0.dist-info/LICENSE
requests_http_signature_jaywink-0.1.0.dev0.dist-info/METADATA
requests_http_signature_jaywink-0.1.0.dev0.dist-info/WHEEL
requests_http_signature_jaywink-0.1.0.dev0.dist-info/top_level.txt
requests_http_signature_jaywink-0.1.0.dev0.dist-info/RECORD
