Metadata-Version: 2.1
Name: requests-http-signature-jaywink
Version: 0.1.0.dev0
Summary: A Requests auth module for HTTP Signature
Home-page: https://github.com/jaywink/requests-http-signature
Author: Andrey Kislyuk
Author-email: kislyuk@gmail.com
License: Apache Software License
Platform: MacOS X
Platform: Posix
Classifier: Intended Audience :: Developers
Classifier: License :: OSI Approved :: Apache Software License
Classifier: Operating System :: MacOS :: MacOS X
Classifier: Operating System :: POSIX
Classifier: Programming Language :: Python
Classifier: Programming Language :: Python :: 2.7
Classifier: Programming Language :: Python :: 3.3
Classifier: Programming Language :: Python :: 3.4
Classifier: Development Status :: 5 - Production/Stable
Classifier: Topic :: Software Development :: Libraries :: Python Modules
Requires-Dist: requests
Provides-Extra: ecdsa
Requires-Dist: cryptography (>=1.8.2) ; extra == 'ecdsa'
Provides-Extra: rsa
Requires-Dist: cryptography (>=1.8.2) ; extra == 'rsa'
